despace/__init__.py
despace/spatial_sort.py
despace/version.py
tests/__init__.py
tests/conftest.py
tests/test_spatial_sort.py
despace-0.3.1.dist-info/LICENSE
despace-0.3.1.dist-info/METADATA
despace-0.3.1.dist-info/WHEEL
despace-0.3.1.dist-info/top_level.txt
despace-0.3.1.dist-info/RECORD
