Metadata-Version: 2.1
Name: despace
Version: 0.3.1
Summary: A spatial decomposition tool for sorting or indexing N-D data.
Home-page: https://github.com/Ruibin-Liu/despace
Author: Ruibin Liu
Author-email: ruibinliuphd@gmail.com
License: UNKNOWN
Project-URL: Bug Tracker, https://github.com/Ruibin-Liu/despace/issues
Platform: UNKNOWN
Classifier: Programming Language :: Python :: 3
Classifier: License :: OSI Approved :: Mozilla Public License 2.0 (MPL 2.0)
Classifier: Operating System :: OS Independent
Requires-Python: >=3.6
License-File: LICENSE
Requires-Dist: numpy (>=1.19)
Requires-Dist: matplotlib (>=3.0)
Provides-Extra: testing
Requires-Dist: tox (>=3.24) ; extra == 'testing'
Requires-Dist: pytest (>=7.0) ; extra == 'testing'
Requires-Dist: pytest-cov (>=3.0) ; extra == 'testing'
